ufo_draw/__init__.py
ufo_draw/main.py
ufo_draw/ufo_diagrams.py
ufo_draw-0.0.6.dist-info/LICENSE
ufo_draw-0.0.6.dist-info/METADATA
ufo_draw-0.0.6.dist-info/WHEEL
ufo_draw-0.0.6.dist-info/entry_points.txt
ufo_draw-0.0.6.dist-info/RECORD
