Metadata-Version: 2.3
Name: ufo_draw
Version: 0.0.6
Summary: Draw Feynman diagrams from UFO models
Author: Alexander Puck Neuwirth
Author-email: alexander@neuwirth-informatik.de
Requires-Python: >=3.8,<4.0
Classifier: Programming Language :: Python :: 3
Classifier: Programming Language :: Python :: 3.8
Classifier: Programming Language :: Python :: 3.9
Classifier: Programming Language :: Python :: 3.10
Classifier: Programming Language :: Python :: 3.11
Classifier: Programming Language :: Python :: 3.12
Classifier: Programming Language :: Python :: 3.13
Requires-Dist: feynml
Requires-Dist: feynmodel (>=0.0.4)
Requires-Dist: pyfeyn2 (>=2.3.4)
Requires-Dist: pyqgraf (>=0.0.8)
Project-URL: Repository, https://github.com/APN-Pucky/ufo-draw
